[
  {
    "alias": "ПР.1",
    "max_grade": 0,
    "name": "Сценарий обучения",
    "type": "Просмотр",
    "week": 1
  },
  {
    "alias": "БДЗ.1",
    "current_grade": 11,
    "max_grade": 16,
    "name": "БДЗ 1 \"Числовые ряды\"",
    "type": "Большое домашнее задание",
    "week": 4
  },
  {
    "alias": "КР.1",
    "max_grade": 6,
    "current_grade": 05,
    "name": "КР 1 \"Ряды\"",
    "type": "Контрольная работа",
    "week": 6
  },
  {
    "alias": "КР.2",
    "max_grade": 12,
    "current_grade": 10,
    "name": "КР 2 \"ДУ первого порядка\"",
    "type": "Контрольная работа",
    "week": 7
  },
  {
    "alias": "К.1",
    "max_grade": 26,
    "current_grade": 11,
    "name": "Коллоквиум 1",
    "type": "Коллоквиум",
    "week": 9
  },
  {
    "alias": "КР.3",
    "max_grade": 10,
    "name": "КР 3 \"ДУ порядка выше первого\"",
    "type": "Контрольная работа",
    "week": 15
  },
  {
    "alias": "КР.4",
    "max_grade": 10,
    "name": "КР 4 \"Системы дифференциальных уравнений\"",
    "type": "Контрольная работа",
    "week": 16
  },
  {
    "alias": "З.1",
    "max_grade": 10,
    "name": "Коллоквиум 2",
    "type": "Зачёт",
    "week": 17
  },
  {
    "alias": "А/П.1",
    "max_grade": 10,
    "type": "Активность/Посещаемость",
    "week": 17
  }
]
